AUTHORS.rst
CONTRIBUTING.rst
HISTORY.rst
LICENSE
MANIFEST.in
README.rst
setup.py
flask_cbv/__init__.py
flask_cbv.egg-info/PKG-INFO
flask_cbv.egg-info/SOURCES.txt
flask_cbv.egg-info/dependency_links.txt
flask_cbv.egg-info/not-zip-safe
flask_cbv.egg-info/requires.txt
flask_cbv.egg-info/top_level.txt
flask_cbv/views/__init__.py
flask_cbv/views/generic.py