Metadata-Version: 1.1
Name: flask-cbv
Version: 0.0.1
Summary: Class based views for Flask.
Home-page: https://bitbucket.org/jsmitka/flask-cbv
Author: Jindřich Smitka
Author-email: smitka.j@gmail.com
License: BSD
Keywords: flask-cbv
Platform: UNKNOWN
Classifier: Development Status :: 2 - Pre-Alpha
Classifier: Intended Audience :: Developers
Classifier: License :: OSI Approved :: BSD License
Classifier: Natural Language :: English
Classifier: Programming Language :: Python :: 2
Classifier: Programming Language :: Python :: 2.6
Classifier: Programming Language :: Python :: 2.7
Classifier: Programming Language :: Python :: 3
Classifier: Programming Language :: Python :: 3.3
